packagecalculator/__init__.py
packagecalculator-0.1.dist-info/LICENSE.txt
packagecalculator-0.1.dist-info/METADATA
packagecalculator-0.1.dist-info/WHEEL
packagecalculator-0.1.dist-info/top_level.txt
packagecalculator-0.1.dist-info/RECORD
