Metadata-Version: 2.1
Name: packagecalculator
Version: 0.1
Summary: <Basic python package Simulator>
Author: <Scarlett H
Author-email: <angelkissan@gmail.com>
Classifier: Programming Language :: Python :: 3
Classifier: License :: OSI Approved :: MIT License
Classifier: Operating System :: OS Independent
License-File: LICENSE.txt
